teams_bot_utils/__init__.py
teams_bot_utils/activity/__init__.py
teams_bot_utils/activity/extensions.py
teams_bot_utils/image/__init__.py
teams_bot_utils/image/processing.py
teams_bot_utils/telemetry/__init__.py
teams_bot_utils/telemetry/mixpanel_telemetry.py
teams_bot_utils/utils/__init__.py
teams_bot_utils/utils/connection_pool.py
teams_bot_utils/utils/http_client.py
teams_bot_utils-1.0.1.dist-info/licenses/LICENSE
teams_bot_utils-1.0.1.dist-info/METADATA
teams_bot_utils-1.0.1.dist-info/WHEEL
teams_bot_utils-1.0.1.dist-info/top_level.txt
teams_bot_utils-1.0.1.dist-info/RECORD
