Metadata-Version: 2.4
Name: teams-bot-utils
Version: 1.0.1
Summary: A comprehensive Python library for Microsoft Teams bot development
Home-page: https://github.com/shubham7995/teams-bot-utils
Author: Shubham Shinde
Author-email: Shubham Shinde <shubhamshinde7995@gmail.com>
License: MIT License
Project-URL: Homepage, https://github.com/shubham7995/teams-bot-utils
Project-URL: Documentation, https://github.com/shubham7995/teams-bot-utils#readme
Project-URL: Repository, https://github.com/shubham7995/teams-bot-utils
Project-URL: Bug Tracker, https://github.com/shubham7995/teams-bot-utils/issues
Classifier: Development Status :: 4 - Beta
Classifier: Intended Audience :: Developers
Classifier: License :: OSI Approved :: MIT License
Classifier: Operating System :: OS Independent
Classifier: Programming Language :: Python :: 3
Classifier: Programming Language :: Python :: 3.8
Classifier: Programming Language :: Python :: 3.9
Classifier: Programming Language :: Python :: 3.10
Classifier: Programming Language :: Python :: 3.11
Classifier: Programming Language :: Python :: 3.12
Classifier: Topic :: Communications :: Chat
Classifier: Topic :: Software Development :: Libraries :: Python Modules
Classifier: Framework :: AsyncIO
Requires-Python: >=3.8
License-File: LICENSE
Requires-Dist: mixpanel>=2.2.0
Requires-Dist: httpx>=0.24.0
Requires-Dist: botbuilder-core>=4.14.0
Requires-Dist: pydantic>=1.8.0
Provides-Extra: dev
Requires-Dist: pytest>=6.0; extra == "dev"
Requires-Dist: pytest-asyncio>=0.18.0; extra == "dev"
Requires-Dist: pytest-cov>=3.0.0; extra == "dev"
Requires-Dist: black>=22.0; extra == "dev"
Requires-Dist: mypy>=0.950; extra == "dev"
Requires-Dist: flake8>=4.0; extra == "dev"
Requires-Dist: pre-commit>=2.15.0; extra == "dev"
Provides-Extra: test
Requires-Dist: pytest>=6.0; extra == "test"
Requires-Dist: pytest-asyncio>=0.18.0; extra == "test"
Requires-Dist: pytest-cov>=3.0.0; extra == "test"
Requires-Dist: pytest-mock>=3.6.0; extra == "test"
Dynamic: author
Dynamic: home-page
Dynamic: license-file
Dynamic: requires-python
